predictor/__init__.py
predictor/crop/__init__.py
predictor/crop/crop.py
predictor/crop/utils.py
predictor/doc/__init__.py
predictor/doc/doc.py
predictor/layout/__init__.py
predictor/layout/layout.py
predictor/text/__init__.py
predictor/text/detector.py
ocr_predictor-0.2.4.dist-info/METADATA
ocr_predictor-0.2.4.dist-info/WHEEL
ocr_predictor-0.2.4.dist-info/top_level.txt
ocr_predictor-0.2.4.dist-info/RECORD
