Metadata-Version: 2.1
Name: ocr-predictor
Version: 0.2.4
Summary: common predictors
Home-page: https://github.com/pbcquoc/predictor
Author: pbcquoc
Author-email: pbcquoc@gmail.com
License: UNKNOWN
Platform: UNKNOWN
Classifier: Programming Language :: Python :: 3
Classifier: License :: OSI Approved :: MIT License
Classifier: Operating System :: OS Independent
Requires-Python: >=3.6
